litestar_cdk_lib/__init__.py
litestar_cdk_lib/app.py
litestar_cdk_lib/auth.py
litestar_cdk_lib/open_api_parser.py
litestar_cdk_lib/python_version.py
litestar_cdk_lib-0.1.6.dist-info/METADATA
litestar_cdk_lib-0.1.6.dist-info/WHEEL
litestar_cdk_lib-0.1.6.dist-info/RECORD
