Metadata-Version: 2.1
Name: litestar-cdk-lib
Version: 0.1.6
Summary: 
Author: kjaye
Author-email: 26447239+KristaBliss@users.noreply.github.com
Requires-Python: >=3.11,<4.0
Classifier: Programming Language :: Python :: 3
Classifier: Programming Language :: Python :: 3.11
Requires-Dist: aws-cdk-lib (>2.0,<3.0)
